saver.py
bineet/FileOperations.py
bineet/TCGA.py
bineet/__init__.py
bineet/bineet.py
bineet/files.py
bineet/saver.py
bineet-0.1.6.dist-info/LICENCE.txt
bineet-0.1.6.dist-info/METADATA
bineet-0.1.6.dist-info/WHEEL
bineet-0.1.6.dist-info/top_level.txt
bineet-0.1.6.dist-info/RECORD
