Metadata-Version: 2.1
Name: bineet
Version: 0.1.6
Summary: Bineet Module
Home-page: UNKNOWN
Author: Bineet Kumar Mohanta
License: UNKNOWN
Platform: UNKNOWN
Classifier: Programming Language :: Python :: 3
Classifier: License :: OSI Approved :: MIT License
Classifier: Operating System :: OS Independent
Requires-Python: >=3.6
License-File: LICENCE.txt
Requires-Dist: pandas (>=1.0.0)
